memorax/__init__.py
memorax/algorithms/__init__.py
memorax/algorithms/dqn.py
memorax/algorithms/ippo.py
memorax/algorithms/ppo.py
memorax/algorithms/pqn.py
memorax/algorithms/r2d2.py
memorax/algorithms/sac.py
memorax/buffers/__init__.py
memorax/buffers/episode_buffer.py
memorax/buffers/prioritised_episode_buffer.py
memorax/environments/__init__.py
memorax/environments/brax.py
memorax/environments/craftax.py
memorax/environments/environment.py
memorax/environments/gxm.py
memorax/environments/gymnax.py
memorax/environments/jaxmarl.py
memorax/environments/mujoco.py
memorax/environments/navix.py
memorax/environments/popgym_arcade.py
memorax/environments/popjym.py
memorax/environments/xminigrid.py
memorax/loggers/__init__.py
memorax/loggers/console.py
memorax/loggers/dashboard.py
memorax/loggers/file.py
memorax/loggers/logger.py
memorax/loggers/neptune.py
memorax/loggers/tensorboard.py
memorax/loggers/wandb.py
memorax/networks/__init__.py
memorax/networks/cnn.py
memorax/networks/embedding.py
memorax/networks/feature_extractor.py
memorax/networks/heads.py
memorax/networks/identity.py
memorax/networks/mlp.py
memorax/networks/network.py
memorax/networks/vit.py
memorax/networks/blocks/__init__.py
memorax/networks/blocks/base.py
memorax/networks/blocks/ffn.py
memorax/networks/blocks/moe.py
memorax/networks/blocks/normalization.py
memorax/networks/blocks/residual.py
memorax/networks/blocks/router.py
memorax/networks/blocks/segment_recurrence.py
memorax/networks/blocks/stack.py
memorax/networks/positional_embeddings/__init__.py
memorax/networks/positional_embeddings/alibi.py
memorax/networks/positional_embeddings/base.py
memorax/networks/positional_embeddings/rope.py
memorax/networks/positional_embeddings/wpe.py
memorax/networks/sequence_models/__init__.py
memorax/networks/sequence_models/ffm.py
memorax/networks/sequence_models/linear_attention.py
memorax/networks/sequence_models/lru.py
memorax/networks/sequence_models/mamba.py
memorax/networks/sequence_models/memoroid.py
memorax-1.0.1.dist-info/licenses/LICENSE
memorax-1.0.1.dist-info/METADATA
memorax-1.0.1.dist-info/WHEEL
memorax-1.0.1.dist-info/top_level.txt
memorax-1.0.1.dist-info/RECORD
