Metadata-Version: 2.4
Name: memorax
Version: 1.0.1
Summary: A unified JAX/Flax framework for memory-augmented reinforcement learning with support for RNNs, SSMs, and Transformers
License-Expression: Apache-2.0
Requires-Python: >=3.11
License-File: LICENSE
Requires-Dist: jax>=0.7.2
Requires-Dist: flax>=0.10.7
Requires-Dist: distrax>=0.1.5
Requires-Dist: flashbax>=0.1.3
Requires-Dist: gymnax>=0.0.9
Requires-Dist: wandb>=0.21.0
Requires-Dist: neptune-scale>=0.27.0
Requires-Dist: tensorboardx>=2.6.4
Provides-Extra: brax
Requires-Dist: brax>=0.12.4; extra == "brax"
Provides-Extra: jumanji
Requires-Dist: jumanji>=1.1.1; extra == "jumanji"
Provides-Extra: navix
Requires-Dist: navix>=0.7.0; extra == "navix"
Provides-Extra: craftax
Requires-Dist: craftax>=1.5.0; extra == "craftax"
Provides-Extra: popgym-arcade
Requires-Dist: popgym-arcade>=0.0.4; extra == "popgym-arcade"
Provides-Extra: playground
Requires-Dist: playground>=0.0.5; extra == "playground"
Requires-Dist: warp-lang>=1.9.1; extra == "playground"
Provides-Extra: gxm
Requires-Dist: gxm; extra == "gxm"
Provides-Extra: popjym
Requires-Dist: popjym; extra == "popjym"
Provides-Extra: xminigrid
Requires-Dist: xminigrid; extra == "xminigrid"
Provides-Extra: jaxmarl
Requires-Dist: jaxmarl; extra == "jaxmarl"
Requires-Dist: brax; extra == "jaxmarl"
Provides-Extra: environments
Requires-Dist: brax>=0.12.4; extra == "environments"
Requires-Dist: gymnax>=0.0.9; extra == "environments"
Requires-Dist: jumanji>=1.1.1; extra == "environments"
Requires-Dist: navix>=0.7.0; extra == "environments"
Requires-Dist: craftax>=1.5.0; extra == "environments"
Requires-Dist: popgym-arcade>=0.0.4; extra == "environments"
Requires-Dist: warp-lang>=1.9.1; extra == "environments"
Requires-Dist: playground>=0.0.5; extra == "environments"
Requires-Dist: jaxmarl==0.1.0; extra == "environments"
Requires-Dist: gxm; extra == "environments"
Requires-Dist: popjym; extra == "environments"
Provides-Extra: cuda
Requires-Dist: jax[cuda12]>=0.7.2; extra == "cuda"
Dynamic: license-file
